odoo8_addon_purchase_picking_state-8.0.1.0.0.99.dev16-py3.8-nspkg.pth
odoo_addons/purchase_picking_state/README.rst
odoo_addons/purchase_picking_state/__init__.py
odoo_addons/purchase_picking_state/__openerp__.py
odoo_addons/purchase_picking_state/purchase.py
odoo_addons/purchase_picking_state/purchase_view.xml
odoo_addons/purchase_picking_state/i18n/de.po
odoo_addons/purchase_picking_state/i18n/es.po
odoo_addons/purchase_picking_state/i18n/fi.po
odoo_addons/purchase_picking_state/i18n/fr.po
odoo_addons/purchase_picking_state/i18n/fr_FR.po
odoo_addons/purchase_picking_state/i18n/it.po
odoo_addons/purchase_picking_state/i18n/nl.po
odoo_addons/purchase_picking_state/i18n/pt_BR.po
odoo_addons/purchase_picking_state/i18n/purchase_picking_state.pot
odoo_addons/purchase_picking_state/i18n/ro.po
odoo_addons/purchase_picking_state/i18n/sl.po
odoo_addons/purchase_picking_state/static/description/icon.png
odoo_addons/purchase_picking_state/tests/__init__.py
odoo_addons/purchase_picking_state/tests/test_purchase_picking_state.py
odoo8_addon_purchase_picking_state-8.0.1.0.0.99.dev16.dist-info/METADATA
odoo8_addon_purchase_picking_state-8.0.1.0.0.99.dev16.dist-info/WHEEL
odoo8_addon_purchase_picking_state-8.0.1.0.0.99.dev16.dist-info/namespace_packages.txt
odoo8_addon_purchase_picking_state-8.0.1.0.0.99.dev16.dist-info/top_level.txt
odoo8_addon_purchase_picking_state-8.0.1.0.0.99.dev16.dist-info/RECORD
